pre_commit_git_checks/__init__.py
pre_commit_git_checks/cli.py
pre_commit_git_checks/hooks/__init__.py
pre_commit_git_checks/hooks/check_git_signoff.py
pre_commit_git_checks/hooks/utils.py
pre_commit_git_checks-0.0.1.dist-info/entry_points.txt
pre_commit_git_checks-0.0.1.dist-info/METADATA
pre_commit_git_checks-0.0.1.dist-info/LICENSE
pre_commit_git_checks-0.0.1.dist-info/WHEEL
pre_commit_git_checks-0.0.1.dist-info/RECORD
