Metadata-Version: 2.1
Name: pre-commit-git-checks
Version: 0.0.1
Summary: A series of basic Git checks meant for linting of your work.
Home-page: https://github.com/KAUTH/pre-commit-git-checks
License: MIT
Keywords: precommit,hooks,git
Author: Konstantinos Papadopoulos
Author-email: konpap1996@yahoo.com
Maintainer: Konstantinos Papadopoulos
Maintainer-email: konpap1996@yahoo.com
Requires-Python: >=3.7,<4.0
Classifier: License :: OSI Approved :: MIT License
Classifier: Natural Language :: English
Classifier: Operating System :: OS Independent
Classifier: Programming Language :: Python
Classifier: Programming Language :: Python :: 3
Classifier: Programming Language :: Python :: 3.7
Classifier: Programming Language :: Python :: 3.8
Classifier: Programming Language :: Python :: 3.9
Classifier: Programming Language :: Python :: 3.10
Classifier: Programming Language :: Python :: 3.11
Classifier: Programming Language :: Python :: 3
Classifier: Programming Language :: Python :: 3.10
Classifier: Programming Language :: Python :: 3.11 
Classifier: Programming Language :: Python :: 3.7
Classifier: Programming Language :: Python :: 3.8
Classifier: Programming Language :: Python :: 3.9
Classifier: Programming Language :: Python :: Implementation :: PyPy
Classifier: Topic :: Software Development
Requires-Dist: click (>=8.1.3,<9.0.0)
Project-URL: Documentation, https://github.com/KAUTH/pre-commit-git-checks/blob/main/README.rst
Project-URL: Repository, https://github.com/KAUTH/pre-commit-git-checks
